thonny_onelight-0.1.dist-info/licenses/LICENSE
thonnycontrib/onelight/__init__.py
thonny_onelight-0.1.dist-info/METADATA
thonny_onelight-0.1.dist-info/WHEEL
thonny_onelight-0.1.dist-info/top_level.txt
thonny_onelight-0.1.dist-info/RECORD
