Metadata-Version: 2.4
Name: thonny-onelight
Version: 0.1
Summary: Atom One Light theme for Thonny IDE
Home-page: https://github.com/Jysume/thonny-onelight
Author: Jysume
Author-email: jysume@outlook.com
License: MIT
Keywords: IDE education programming Thonny light theme onelight
Platform: Windows
Platform: macOS
Platform: Linux
Classifier: Intended Audience :: Developers
Classifier: Intended Audience :: Education
Classifier: Intended Audience :: End Users/Desktop
Classifier: License :: OSI Approved :: MIT License
Classifier: Operating System :: MacOS
Classifier: Operating System :: Microsoft :: Windows
Classifier: Operating System :: POSIX
Classifier: Operating System :: POSIX :: Linux
Classifier: Programming Language :: Python
Classifier: Programming Language :: Python :: 3
Classifier: Topic :: Education
Classifier: Topic :: Software Development
Classifier: Topic :: Software Development :: Embedded Systems
License-File: LICENSE
Requires-Dist: thonny>=3.0.0
Dynamic: author
Dynamic: author-email
Dynamic: classifier
Dynamic: description
Dynamic: home-page
Dynamic: keywords
Dynamic: license
Dynamic: license-file
Dynamic: platform
Dynamic: requires-dist
Dynamic: summary
